obfsc8/__init__.py
obfsc8/get_columns_to_be_obfuscated.py
obfsc8/get_file_object_from_s3_bucket.py
obfsc8/get_filetype.py
obfsc8/get_s3_bucket_and_key_names.py
obfsc8/obfuscate.py
obfsc8/obfuscate_csv_file.py
obfsc8/obfuscate_json_file.py
obfsc8/obfuscate_parquet_file.py
obfsc8-1.0.1.dist-info/LICENSE
obfsc8-1.0.1.dist-info/METADATA
obfsc8-1.0.1.dist-info/WHEEL
obfsc8-1.0.1.dist-info/top_level.txt
obfsc8-1.0.1.dist-info/RECORD
