Metadata-Version: 2.1
Name: obfsc8
Version: 1.0.1
Summary: Easy obfuscation of Personally Identifiable Information (PII) within Amazon S3 files
Project-URL: Homepage, https://github.com/jambent/gdpr_obfuscator
Project-URL: Changelog, https://github.com/jambent/gdpr_obfuscator/releases
Project-URL: Issues, https://github.com/jambent/gdpr_obfuscator/issues
Classifier: License :: OSI Approved :: MIT License
Requires-Python: >=3.10
License-File: LICENSE
Requires-Dist: boto3
Requires-Dist: polars
